{"config":{"output_file":null,"full_docs":false,"pub_only":true,"reachable_only":true,"distro_crate":false,"signatures":false,"borrow_data":false},"version":"0.18.1","compilation":{"directory":[47,104,111,109,101,47,107,50,47,46,99,97,114,103,111,47,114,101,103,105,115,116,114,121,47,115,114,99,47,103,105,116,104,117,98,46,99,111,109,45,49,101,99,99,54,50,57,57,100,98,57,101,99,56,50,51,47,116,101,120,116,95,105,111,45,48,46,49,46,55],"program":"/home/k2/.rustup/toolchains/nightly-x86_64-unknown-linux-gnu/bin/rls","arguments":["--crate-name","text_io","/home/k2/.cargo/registry/src/github.com-1ecc6299db9ec823/text_io-0.1.7/src/lib.rs","--color","never","--crate-type","lib","--emit=dep-info,metadata","-C","debuginfo=2","-C","metadata=c25efc1effa52dbd","-C","extra-filename=-c25efc1effa52dbd","--out-dir","/home/k2/Workbench/jade-signer/target/rls/debug/deps","-L","dependency=/home/k2/Workbench/jade-signer/target/rls/debug/deps","--cap-lints","allow","--error-format=json","--sysroot","/home/k2/.rustup/toolchains/nightly-x86_64-unknown-linux-gnu"],"output":[47,104,111,109,101,47,107,50,47,87,111,114,107,98,101,110,99,104,47,106,97,100,101,45,115,105,103,110,101,114,47,116,97,114,103,101,116,47,114,108,115,47,100,101,98,117,103,47,100,101,112,115,47,108,105,98,116,101,120,116,95,105,111,45,99,50,53,101,102,99,49,101,102,102,97,53,50,100,98,100,46,114,109,101,116,97]},"prelude":{"crate_id":{"name":"text_io","disambiguator":[7584676188390727405,2153520867575352169]},"crate_root":"/home/k2/.cargo/registry/src/github.com-1ecc6299db9ec823/text_io-0.1.7/src","external_crates":[{"file_name":"/home/k2/.cargo/registry/src/github.com-1ecc6299db9ec823/text_io-0.1.7/src/lib.rs","num":1,"id":{"name":"std","disambiguator":[7643654914076001483,12823312228256817667]}},{"file_name":"/home/k2/.cargo/registry/src/github.com-1ecc6299db9ec823/text_io-0.1.7/src/lib.rs","num":2,"id":{"name":"core","disambiguator":[4460275713293065345,16951895692468253576]}},{"file_name":"/home/k2/.cargo/registry/src/github.com-1ecc6299db9ec823/text_io-0.1.7/src/lib.rs","num":3,"id":{"name":"compiler_builtins","disambiguator":[11180861269583930402,7218748977825450810]}},{"file_name":"/home/k2/.cargo/registry/src/github.com-1ecc6299db9ec823/text_io-0.1.7/src/lib.rs","num":4,"id":{"name":"rustc_std_workspace_core","disambiguator":[4642033898704731799,9729154345420223309]}},{"file_name":"/home/k2/.cargo/registry/src/github.com-1ecc6299db9ec823/text_io-0.1.7/src/lib.rs","num":5,"id":{"name":"alloc","disambiguator":[12818274104326731107,682062526801359143]}},{"file_name":"/home/k2/.cargo/registry/src/github.com-1ecc6299db9ec823/text_io-0.1.7/src/lib.rs","num":6,"id":{"name":"libc","disambiguator":[12755702926841618597,12055052820604553981]}},{"file_name":"/home/k2/.cargo/registry/src/github.com-1ecc6299db9ec823/text_io-0.1.7/src/lib.rs","num":7,"id":{"name":"rustc_demangle","disambiguator":[1437492519896548358,983587994810570921]}},{"file_name":"/home/k2/.cargo/registry/src/github.com-1ecc6299db9ec823/text_io-0.1.7/src/lib.rs","num":8,"id":{"name":"unwind","disambiguator":[15755932282147130284,14837425147787014863]}},{"file_name":"/home/k2/.cargo/registry/src/github.com-1ecc6299db9ec823/text_io-0.1.7/src/lib.rs","num":9,"id":{"name":"backtrace_sys","disambiguator":[14848937618377221952,4542086914855755700]}},{"file_name":"/home/k2/.cargo/registry/src/github.com-1ecc6299db9ec823/text_io-0.1.7/src/lib.rs","num":10,"id":{"name":"panic_unwind","disambiguator":[1423741341053305533,4588337216884661599]}}],"span":{"file_name":[47,104,111,109,101,47,107,50,47,46,99,97,114,103,111,47,114,101,103,105,115,116,114,121,47,115,114,99,47,103,105,116,104,117,98,46,99,111,109,45,49,101,99,99,54,50,57,57,100,98,57,101,99,56,50,51,47,116,101,120,116,95,105,111,45,48,46,49,46,55,47,115,114,99,47,108,105,98,46,114,115],"byte_start":0,"byte_end":7526,"line_start":1,"line_end":246,"column_start":1,"column_end":3}},"imports":[],"defs":[{"kind":"Mod","id":{"krate":0,"index":0},"span":{"file_name":[47,104,111,109,101,47,107,50,47,46,99,97,114,103,111,47,114,101,103,105,115,116,114,121,47,115,114,99,47,103,105,116,104,117,98,46,99,111,109,45,49,101,99,99,54,50,57,57,100,98,57,101,99,56,50,51,47,116,101,120,116,95,105,111,45,48,46,49,46,55,47,115,114,99,47,108,105,98,46,114,115],"byte_start":0,"byte_end":7526,"line_start":1,"line_end":246,"column_start":1,"column_end":3},"name":"","qualname":"::","value":"/home/k2/.cargo/registry/src/github.com-1ecc6299db9ec823/text_io-0.1.7/src/lib.rs","parent":null,"children":[{"krate":0,"index":2},{"krate":0,"index":4},{"krate":0,"index":6},{"krate":0,"index":8},{"krate":0,"index":10},{"krate":0,"index":40},{"krate":0,"index":48},{"krate":0,"index":42},{"krate":0,"index":12},{"krate":0,"index":18},{"krate":0,"index":26},{"krate":0,"index":28},{"krate":0,"index":32},{"krate":0,"index":34},{"krate":0,"index":36},{"krate":0,"index":38}],"decl_id":null,"docs":" This crate allows one-liners to read from a terminal\n A minimal example to get an i32 from the command line is","sig":null,"attributes":[]},{"kind":"TupleVariant","id":{"krate":0,"index":29},"span":{"file_name":[47,104,111,109,101,47,107,50,47,46,99,97,114,103,111,47,114,101,103,105,115,116,114,121,47,115,114,99,47,103,105,116,104,117,98,46,99,111,109,45,49,101,99,99,54,50,57,57,100,98,57,101,99,56,50,51,47,116,101,120,116,95,105,111,45,48,46,49,46,55,47,115,114,99,47,108,105,98,46,114,115],"byte_start":1033,"byte_end":1045,"line_start":39,"line_end":39,"column_start":5,"column_end":17},"name":"MissingMatch","qualname":"::Error::MissingMatch","value":"Error::MissingMatch","parent":{"krate":0,"index":40},"children":[],"decl_id":null,"docs":"","sig":null,"attributes":[]},{"kind":"TupleVariant","id":{"krate":0,"index":31},"span":{"file_name":[47,104,111,109,101,47,107,50,47,46,99,97,114,103,111,47,114,101,103,105,115,116,114,121,47,115,114,99,47,103,105,116,104,117,98,46,99,111,109,45,49,101,99,99,54,50,57,57,100,98,57,101,99,56,50,51,47,116,101,120,116,95,105,111,45,48,46,49,46,55,47,115,114,99,47,108,105,98,46,114,115],"byte_start":1051,"byte_end":1070,"line_start":40,"line_end":40,"column_start":5,"column_end":24},"name":"MissingClosingBrace","qualname":"::Error::MissingClosingBrace","value":"Error::MissingClosingBrace","parent":{"krate":0,"index":40},"children":[],"decl_id":null,"docs":"","sig":null,"attributes":[]},{"kind":"TupleVariant","id":{"krate":0,"index":33},"span":{"file_name":[47,104,111,109,101,47,107,50,47,46,99,97,114,103,111,47,114,101,103,105,115,116,114,121,47,115,114,99,47,103,105,116,104,117,98,46,99,111,109,45,49,101,99,99,54,50,57,57,100,98,57,101,99,56,50,51,47,116,101,120,116,95,105,111,45,48,46,49,46,55,47,115,114,99,47,108,105,98,46,114,115],"byte_start":1076,"byte_end":1091,"line_start":41,"line_end":41,"column_start":5,"column_end":20},"name":"UnexpectedValue","qualname":"::Error::UnexpectedValue","value":"Error::UnexpectedValue(u8, Option<u8>)","parent":{"krate":0,"index":40},"children":[],"decl_id":null,"docs":"","sig":null,"attributes":[]},{"kind":"TupleVariant","id":{"krate":0,"index":39},"span":{"file_name":[47,104,111,109,101,47,107,50,47,46,99,97,114,103,111,47,114,101,103,105,115,116,114,121,47,115,114,99,47,103,105,116,104,117,98,46,99,111,109,45,49,101,99,99,54,50,57,57,100,98,57,101,99,56,50,51,47,116,101,120,116,95,105,111,45,48,46,49,46,55,47,115,114,99,47,108,105,98,46,114,115],"byte_start":1113,"byte_end":1124,"line_start":42,"line_end":42,"column_start":5,"column_end":16},"name":"InvalidUtf8","qualname":"::Error::InvalidUtf8","value":"Error::InvalidUtf8(Vec<u8>)","parent":{"krate":0,"index":40},"children":[],"decl_id":null,"docs":"","sig":null,"attributes":[]},{"kind":"TupleVariant","id":{"krate":0,"index":43},"span":{"file_name":[47,104,111,109,101,47,107,50,47,46,99,97,114,103,111,47,114,101,103,105,115,116,114,121,47,115,114,99,47,103,105,116,104,117,98,46,99,111,109,45,49,101,99,99,54,50,57,57,100,98,57,101,99,56,50,51,47,116,101,120,116,95,105,111,45,48,46,49,46,55,47,115,114,99,47,108,105,98,46,114,115],"byte_start":1139,"byte_end":1150,"line_start":43,"line_end":43,"column_start":5,"column_end":16},"name":"PartialUtf8","qualname":"::Error::PartialUtf8","value":"Error::PartialUtf8(usize, Vec<u8>)","parent":{"krate":0,"index":40},"children":[],"decl_id":null,"docs":"","sig":null,"attributes":[]},{"kind":"TupleVariant","id":{"krate":0,"index":49},"span":{"file_name":[47,104,111,109,101,47,107,50,47,46,99,97,114,103,111,47,114,101,103,105,115,116,114,121,47,115,114,99,47,103,105,116,104,117,98,46,99,111,109,45,49,101,99,99,54,50,57,57,100,98,57,101,99,56,50,51,47,116,101,120,116,95,105,111,45,48,46,49,46,55,47,115,114,99,47,108,105,98,46,114,115],"byte_start":1172,"byte_end":1177,"line_start":44,"line_end":44,"column_start":5,"column_end":10},"name":"Parse","qualname":"::Error::Parse","value":"Error::Parse(String, &'static str)","parent":{"krate":0,"index":40},"children":[],"decl_id":null,"docs":"","sig":null,"attributes":[]},{"kind":"TupleVariant","id":{"krate":0,"index":55},"span":{"file_name":[47,104,111,109,101,47,107,50,47,46,99,97,114,103,111,47,114,101,103,105,115,116,114,121,47,115,114,99,47,103,105,116,104,117,98,46,99,111,109,45,49,101,99,99,54,50,57,57,100,98,57,101,99,56,50,51,47,116,101,120,116,95,105,111,45,48,46,49,46,55,47,115,114,99,47,108,105,98,46,114,115],"byte_start":1224,"byte_end":1241,"line_start":46,"line_end":46,"column_start":5,"column_end":22},"name":"__NonExhaustive__","qualname":"::Error::__NonExhaustive__","value":"Error::__NonExhaustive__","parent":{"krate":0,"index":40},"children":[],"decl_id":null,"docs":"","sig":null,"attributes":[]},{"kind":"Enum","id":{"krate":0,"index":40},"span":{"file_name":[47,104,111,109,101,47,107,50,47,46,99,97,114,103,111,47,114,101,103,105,115,116,114,121,47,115,114,99,47,103,105,116,104,117,98,46,99,111,109,45,49,101,99,99,54,50,57,57,100,98,57,101,99,56,50,51,47,116,101,120,116,95,105,111,45,48,46,49,46,55,47,115,114,99,47,108,105,98,46,114,115],"byte_start":1021,"byte_end":1026,"line_start":38,"line_end":38,"column_start":10,"column_end":15},"name":"Error","qualname":"::Error","value":"Error::{MissingMatch, MissingClosingBrace, UnexpectedValue, InvalidUtf8, PartialUtf8, Parse, __NonExhaustive__}","parent":null,"children":[{"krate":0,"index":29},{"krate":0,"index":31},{"krate":0,"index":33},{"krate":0,"index":39},{"krate":0,"index":43},{"krate":0,"index":49},{"krate":0,"index":55}],"decl_id":null,"docs":"","sig":null,"attributes":[]},{"kind":"Function","id":{"krate":0,"index":26},"span":{"file_name":[47,104,111,109,101,47,107,50,47,46,99,97,114,103,111,47,114,101,103,105,115,116,114,121,47,115,114,99,47,103,105,116,104,117,98,46,99,111,109,45,49,101,99,99,54,50,57,57,100,98,57,101,99,56,50,51,47,116,101,120,116,95,105,111,45,48,46,49,46,55,47,115,114,99,47,108,105,98,46,114,115],"byte_start":2778,"byte_end":2788,"line_start":90,"line_end":90,"column_start":8,"column_end":18},"name":"match_next","qualname":"::match_next","value":"fn (expected: u8, iter: &mut Iterator<Item = u8>) -> Result<(), Error>","parent":null,"children":[],"decl_id":null,"docs":"","sig":null,"attributes":[]},{"kind":"Function","id":{"krate":0,"index":28},"span":{"file_name":[47,104,111,109,101,47,107,50,47,46,99,97,114,103,111,47,114,101,103,105,115,116,114,121,47,115,114,99,47,103,105,116,104,117,98,46,99,111,109,45,49,101,99,99,54,50,57,57,100,98,57,101,99,56,50,51,47,116,101,120,116,95,105,111,45,48,46,49,46,55,47,115,114,99,47,108,105,98,46,114,115],"byte_start":3005,"byte_end":3018,"line_start":98,"line_end":98,"column_start":8,"column_end":21},"name":"parse_capture","qualname":"::parse_capture","value":"fn <T> (name: &'static str, next: Option<u8>, iter: &mut Iterator<Item = u8>) -> Result<T, Error>","parent":null,"children":[],"decl_id":null,"docs":"","sig":null,"attributes":[]}],"impls":[{"id":0,"kind":"Direct","span":{"file_name":[47,104,111,109,101,47,107,50,47,46,99,97,114,103,111,47,114,101,103,105,115,116,114,121,47,115,114,99,47,103,105,116,104,117,98,46,99,111,109,45,49,101,99,99,54,50,57,57,100,98,57,101,99,56,50,51,47,116,101,120,116,95,105,111,45,48,46,49,46,55,47,115,114,99,47,108,105,98,46,114,115],"byte_start":1268,"byte_end":1273,"line_start":49,"line_end":49,"column_start":23,"column_end":28},"value":"","parent":null,"children":[{"krate":0,"index":14}],"docs":"","sig":null,"attributes":[]},{"id":1,"kind":"Direct","span":{"file_name":[47,104,111,109,101,47,107,50,47,46,99,97,114,103,111,47,114,101,103,105,115,116,114,121,47,115,114,99,47,103,105,116,104,117,98,46,99,111,109,45,49,101,99,99,54,50,57,57,100,98,57,101,99,56,50,51,47,116,101,120,116,95,105,111,45,48,46,49,46,55,47,115,114,99,47,108,105,98,46,114,115],"byte_start":1893,"byte_end":1898,"line_start":65,"line_end":65,"column_start":23,"column_end":28},"value":"","parent":null,"children":[{"krate":0,"index":20}],"docs":"","sig":null,"attributes":[]}],"refs":[],"macro_refs":[],"relations":[{"span":{"file_name":[47,104,111,109,101,47,107,50,47,46,99,97,114,103,111,47,114,101,103,105,115,116,114,121,47,115,114,99,47,103,105,116,104,117,98,46,99,111,109,45,49,101,99,99,54,50,57,57,100,98,57,101,99,56,50,51,47,116,101,120,116,95,105,111,45,48,46,49,46,55,47,115,114,99,47,108,105,98,46,114,115],"byte_start":1268,"byte_end":1273,"line_start":49,"line_end":49,"column_start":23,"column_end":28},"kind":{"variant":"Impl","fields":[0]},"from":{"krate":0,"index":40},"to":{"krate":1,"index":2466}},{"span":{"file_name":[47,104,111,109,101,47,107,50,47,46,99,97,114,103,111,47,114,101,103,105,115,116,114,121,47,115,114,99,47,103,105,116,104,117,98,46,99,111,109,45,49,101,99,99,54,50,57,57,100,98,57,101,99,56,50,51,47,116,101,120,116,95,105,111,45,48,46,49,46,55,47,115,114,99,47,108,105,98,46,114,115],"byte_start":1893,"byte_end":1898,"line_start":65,"line_end":65,"column_start":23,"column_end":28},"kind":{"variant":"Impl","fields":[1]},"from":{"krate":0,"index":40},"to":{"krate":2,"index":8404}}]}